yaslha/__init__.py
yaslha/_collections.py
yaslha/_collections.pyi
yaslha/_line.py
yaslha/block.py
yaslha/comment.py
yaslha/comment.pyi
yaslha/config.py
yaslha/dumper.py
yaslha/line.py
yaslha/parser.py
yaslha/py.typed
yaslha/script.py
yaslha/slha.py
yaslha/tests/__init__.py
yaslha/tests/data/SPheno-2.spc.MSSM
yaslha/tests/data/SPheno.spc
yaslha/tests/data/SPheno.spc.MSSM
yaslha/tests/data/isajet.txt
yaslha/tests/data/isasusy.spc
yaslha/tests/data/pylha_json/SPheno-2.spc.MSSM.json
yaslha/tests/data/pylha_json/SPheno.spc.MSSM.json
yaslha/tests/data/pylha_json/SPheno.spc.json
yaslha/tests/data/pylha_json/isajet.txt.json
yaslha/tests/data/pylha_json/isasusy.spc.json
yaslha/tests/data/pylha_json/sdecay.bin.json
yaslha/tests/data/pylha_json/slha.txt.json
yaslha/tests/data/pylha_json/softsusy.spc.json
yaslha/tests/data/pylha_json/sps1a.spc.json
yaslha/tests/data/pylha_yaml/SPheno-2.spc.MSSM.yaml
yaslha/tests/data/pylha_yaml/SPheno.spc.MSSM.yaml
yaslha/tests/data/pylha_yaml/SPheno.spc.yaml
yaslha/tests/data/pylha_yaml/isajet.txt.yaml
yaslha/tests/data/pylha_yaml/isasusy.spc.yaml
yaslha/tests/data/pylha_yaml/sdecay.bin.yaml
yaslha/tests/data/pylha_yaml/slha.txt.yaml
yaslha/tests/data/pylha_yaml/softsusy.spc.yaml
yaslha/tests/data/pylha_yaml/sps1a.spc.yaml
yaslha/tests/data/sdecay.bin
yaslha/tests/data/slha.txt
yaslha/tests/data/softsusy.spc
yaslha/tests/data/sps1a.spc
yaslha/tests/examples/test_example1_basic.py
yaslha/tests/examples/test_example2_simple.py
yaslha/tests/examples/test_example3_advanced.py
yaslha/tests/examples/test_example4_decay.py
yaslha/tests/examples/test_example5_blocks.py
yaslha/tests/examples/test_example6_comment.py
yaslha/tests/test_collections.py
yaslha/tests/test_converter.py
yaslha/tests/test_copy.py
yaslha/utility.py
yaslha/yaslha.cfg.default
yaslha-0.3.4.dist-info/entry_points.txt
yaslha-0.3.4.dist-info/LICENSE
yaslha-0.3.4.dist-info/WHEEL
yaslha-0.3.4.dist-info/METADATA
yaslha-0.3.4.dist-info/RECORD
