Metadata-Version: 2.1
Name: yaslha
Version: 0.3.4
Summary: A Python package to handle SLHA (SUSY Les Houches Accord) files.
Home-page: https://github.com/misho104/yaslha
License: MIT
Author: Sho Iwamoto (Misho)
Author-email: webmaster@misho-web.com
Requires-Python: >=3.8,<4.0
Classifier: License :: OSI Approved :: MIT License
Classifier: Programming Language :: Python :: 3
Classifier: Programming Language :: Python :: 3.10
Classifier: Programming Language :: Python :: 3.8
Classifier: Programming Language :: Python :: 3.9
Requires-Dist: click (>=8.1,<9.0)
Requires-Dist: colorama (>=0.4.4,<0.5.0)
Requires-Dist: coloredlogs (>=15.0,<16.0)
Requires-Dist: numpy (>=1.23,<2.0)
Requires-Dist: ruamel.yaml (>=0.17.4,<0.18.0)
Requires-Dist: typing-extensions (>=4.0,<5.0)
Project-URL: Repository, https://github.com/misho104/yaslha
